ezserve/__init__.py
ezserve/__main__.py
ezserve-0.2.0.dist-info/LICENSE
ezserve-0.2.0.dist-info/METADATA
ezserve-0.2.0.dist-info/WHEEL
ezserve-0.2.0.dist-info/top_level.txt
ezserve-0.2.0.dist-info/RECORD
