Metadata-Version: 2.1
Name: ezserve
Version: 0.2.0
Summary: A simple way to share files over HTTP without explaining FTP to the receiver.
Author-email: Farm-Art <github@farmart.tech>
License: This is free and unencumbered software released into the public domain.
Project-URL: Homepage, https://github.com/Farm-Art/EZserve
Project-URL: Issues, https://github.com/Farm-Art/EZserve/issues
Keywords: server,serve,easy,http,cli
Classifier: Programming Language :: Python :: 3
Classifier: Operating System :: OS Independent
Requires-Python: >=3.12
License-File: LICENSE
Requires-Dist: bottle >=0.13.1
